gimmebio.cli-0.1.7-py3.6-nspkg.pth
gimmebio/cli/__init__.py
gimmebio/cli/cli.py
gimmebio/cli/mycli.py
gimmebio.cli-0.1.7.dist-info/METADATA
gimmebio.cli-0.1.7.dist-info/WHEEL
gimmebio.cli-0.1.7.dist-info/entry_points.txt
gimmebio.cli-0.1.7.dist-info/namespace_packages.txt
gimmebio.cli-0.1.7.dist-info/top_level.txt
gimmebio.cli-0.1.7.dist-info/RECORD
